testpypipkgtest/__init__.py
testpypipkgtest-0.1.1.dist-info/METADATA
testpypipkgtest-0.1.1.dist-info/WHEEL
testpypipkgtest-0.1.1.dist-info/top_level.txt
testpypipkgtest-0.1.1.dist-info/RECORD
